<?xml version="1.0" encoding="utf-8"?>
<Trias version="1.2" xmlns="http://www.vdv.de/trias" xmlns:siri="http://www.siri.org.uk/siri" xmlns:xsi="http://www.w3.org/2001/XMLSchema-instance" xsi:schemaLocation="http://www.vdv.de/trias ../trias-xsd-v1.1/Trias.xsd">
	<ServiceRequest>
		<siri:RequestTimestamp>1990-01-01T00:00:00Z</siri:RequestTimestamp>
		<siri:RequestorRef>needsToBeFilled</siri:RequestorRef>
		<siri:MessageIdentifier>4711</siri:MessageIdentifier>
		<RequestPayload>
			<TripInfoRequest>
				<JourneyRef>needsToBeFilled</JourneyRef>
				<OperatingDayRef>1990-01-01T</OperatingDayRef>
				<Params>                   
                    <UseTimetabledDataOnly>false</UseTimetabledDataOnly>
                    <IncludeCalls>true</IncludeCalls>                    
                    <IncludeService>true</IncludeService>
                </Params>
			</TripInfoRequest>
		</RequestPayload>
	</ServiceRequest>
</Trias>
